djangoadmin/__init__.py
djangoadmin/admin.py
djangoadmin/apps.py
djangoadmin/urls.py
djangoadmin/extra/ImageUploadDestination.py
djangoadmin/extra/__init__.py
djangoadmin/middlewares/AuthenticationStatusMiddleware.py
djangoadmin/middlewares/__init__.py
djangoadmin/migrations/0001_initial.py
djangoadmin/migrations/__init__.py
djangoadmin/modeladmins/UserModelAdmin.py
djangoadmin/modeladmins/__init__.py
djangoadmin/modelforms/EditProfileModelForm.py
djangoadmin/modelforms/RegistrationModelForm.py
djangoadmin/modelforms/SigninModelForm.py
djangoadmin/modelforms/UserModelForm.py
djangoadmin/modelforms/__init__.py
djangoadmin/models/UserModel.py
djangoadmin/models/__init__.py
djangoadmin/rest_api/__init__.py
djangoadmin/rest_api/urls.py
djangoadmin/rest_api/serializers/UserModelSerializer.py
djangoadmin/rest_api/serializers/UserProfileSerializer.py
djangoadmin/rest_api/serializers/UserRegistrationSerializer.py
djangoadmin/rest_api/serializers/__init__.py
djangoadmin/rest_api/viewsets/UserModelRetrieveViewSet.py
djangoadmin/rest_api/viewsets/UserProfileViewSet.py
djangoadmin/rest_api/viewsets/UserRegistrationViewSet.py
djangoadmin/rest_api/viewsets/__init__.py
djangoadmin/signals/__init__.py
djangoadmin/signals/createUserProfile.py
djangoadmin/templates/djangoadmin/djangoadmin/account_view_dashboard.html
djangoadmin/templates/djangoadmin/djangoadmin/edit_profile_view_form.html
djangoadmin/templates/djangoadmin/djangoadmin/login_view_form.html
djangoadmin/templates/djangoadmin/djangoadmin/password_change_view_form.html
djangoadmin/templates/djangoadmin/djangoadmin/password_reset_complete_view.html
djangoadmin/templates/djangoadmin/djangoadmin/password_reset_confirm_view.html
djangoadmin/templates/djangoadmin/djangoadmin/password_reset_done_view.html
djangoadmin/templates/djangoadmin/djangoadmin/password_reset_email.html
djangoadmin/templates/djangoadmin/djangoadmin/password_reset_view.html
djangoadmin/templates/djangoadmin/djangoadmin/profile_view_dashboard.html
djangoadmin-2.2.8.dist-info/License
djangoadmin-2.2.8.dist-info/METADATA
djangoadmin-2.2.8.dist-info/WHEEL
djangoadmin-2.2.8.dist-info/top_level.txt
djangoadmin-2.2.8.dist-info/RECORD
